strands_agents_sops/__init__.py
strands_agents_sops/__main__.py
strands_agents_sops/cursor.py
strands_agents_sops/mcp.py
strands_agents_sops/rules.py
strands_agents_sops/skills.py
strands_agents_sops/utils.py
strands_agents_sops/rules/agent-sop-format.md
strands_agents_sops/sops/code-assist.sop.md
strands_agents_sops/sops/code-task-generator.sop.md
strands_agents_sops/sops/codebase-summary.sop.md
strands_agents_sops/sops/eval.sop.md
strands_agents_sops/sops/pdd.sop.md
strands_agents_sops-1.0.5.dist-info/METADATA
strands_agents_sops-1.0.5.dist-info/WHEEL
strands_agents_sops-1.0.5.dist-info/entry_points.txt
strands_agents_sops-1.0.5.dist-info/RECORD
