Metadata-Version: 2.4
Name: strands-agents-sops
Version: 1.0.5
Summary: Natural language workflows that enable AI agents to perform complex, multi-step tasks with consistency and reliability
License: Apache-2.0
Requires-Python: >=3.10
Requires-Dist: mcp>=1.20.0
